pages/__init__.py
pages/base_page.py
pages/forgot_page.py
pages/location_page.py
pages/login_page.py
pages/register_page.py
tests/__init__.py
tests/forgot_test.py
tests/login_test_android.py
tests/test_all.py
tests/test_login.py
tests/test_register.py
tests/test_script.py
zenwel_biz2-0.1.0.dist-info/METADATA
zenwel_biz2-0.1.0.dist-info/WHEEL
zenwel_biz2-0.1.0.dist-info/top_level.txt
zenwel_biz2-0.1.0.dist-info/RECORD
