Metadata-Version: 2.1
Name: zenwel-biz2
Version: 0.1.0
Summary: Deskripsi singkat paket Anda
Home-page: https://github.com/olseraqa/zenwel-biz.git
Author: Adit
Author-email: aditbekerja@gmail.com
Classifier: Programming Language :: Python :: 3
Classifier: License :: OSI Approved :: MIT License
Classifier: Operating System :: OS Independent
